[
  {
    "txid": "9a222f0e9e176e5a70c95dbbe59afce6607bb5a50c7ef96ea91fa49f8f14525e",
    "vout": 1,
    "executionStatus": {
      "status": "unknown",
      "reason": "No trace data available"
    },
    "hasTraceData": false,
    "timestamp": "2025-03-11T23:36:48.396Z"
  },
  {
    "txid": "2cf4a155572450d6595e31b62645e50c8b5fa82d91c8e0e586f394d2f4b1ca7c",
    "vout": 0,
    "executionStatus": {
      "status": "unknown",
      "reason": "No trace data available"
    },
    "hasTraceData": false,
    "timestamp": "2025-03-11T23:36:48.443Z"
  }
]